{
  "name": "Classes",
  "_id": "H76xJMaOJFmWpDIm",
  "pages": [
    {
      "sort": 100000,
      "name": "Overview",
      "type": "text",
      "_id": "xumDsH85X7KxLhTH",
      "system": {},
      "title": {
        "show": true,
        "level": 1
      },
      "image": {},
      "text": {
        "format": 1,
        "content": "<p>Character class provides a character’s most exciting capabilities. Materia offers fifteen classes, each of which contains numerous subclasses—all summarized below.</p><h3>@UUID[Compendium.materia-dnd.rules.JournalEntry.xL1RnhxE3qZRDvml.JournalEntryPage.ZR7GN14L9OzoBpnX]{Artificer}</h3><p>Masters of invention, artificers use ingenuity and magic to unlock extraordinary capabilities in objects.</p><p><em>Subclasses</em>:</p><ul><li><p><strong>@UUID[Compendium.materia-dnd.rules.JournalEntry.xL1RnhxE3qZRDvml.JournalEntryPage.qNbZBg3nesuzmTFG]{Alchemist}</strong></p></li><li><p><strong>@UUID[Compendium.materia-dnd.rules.JournalEntry.xL1RnhxE3qZRDvml.JournalEntryPage.7JU24wXFLeRzr9lE]{Armorer}</strong></p></li><li><p><strong>@UUID[Compendium.materia-dnd.rules.JournalEntry.xL1RnhxE3qZRDvml.JournalEntryPage.WbtfTidGoU0VgcSn]{Artillerist}</strong></p></li><li><p><strong>@UUID[Compendium.materia-dnd.rules.JournalEntry.xL1RnhxE3qZRDvml.JournalEntryPage.9Y08om1k7kVmsgeC]{Battle Smith}</strong></p></li></ul><h3>@UUID[Compendium.materia-dnd.rules.JournalEntry.2pzEa0ZH8CFn7sOC.JournalEntryPage.OZLPwhhNwauBSIxJ]{Barbarian}</h3><p>A fierce warrior who can enter a battle rage.</p><p><em>Subclasses</em>:</p><ul><li><p><strong>@UUID[Compendium.materia-dnd.rules.JournalEntry.2pzEa0ZH8CFn7sOC.JournalEntryPage.8pW35AUoadwx2UhB]{Path of the Ancestral Guardian}</strong></p></li><li><p><strong>@UUID[Compendium.materia-dnd.rules.JournalEntry.2pzEa0ZH8CFn7sOC.JournalEntryPage.uesqhyBt1giefx3m]{Path of the Beast}</strong></p></li><li><p><strong>@UUID[Compendium.materia-dnd.rules.JournalEntry.2pzEa0ZH8CFn7sOC.JournalEntryPage.rKKPoNZrkw3FnqMx]{Path of the Berserker}</strong></p></li><li><p><strong>@UUID[Compendium.materia-dnd.rules.JournalEntry.2pzEa0ZH8CFn7sOC.JournalEntryPage.QUgBjpMqYLzHNcIC]{Path of the Giant}</strong></p></li><li><p><strong>@UUID[Compendium.materia-dnd.rules.JournalEntry.2pzEa0ZH8CFn7sOC.JournalEntryPage.hvbIWLyoSm51oQWs]{Path of the Storm Herald}</strong></p></li><li><p><strong>@UUID[Compendium.materia-dnd.rules.JournalEntry.2pzEa0ZH8CFn7sOC.JournalEntryPage.SwQmox9zdsABgL1d]{Path of the Totem Warrior}</strong></p></li><li><p><strong>@UUID[Compendium.materia-dnd.rules.JournalEntry.2pzEa0ZH8CFn7sOC.JournalEntryPage.aWMOUfjmA7pB6hLd]{Path of the Zealot}</strong></p></li><li><p><strong>@UUID[Compendium.materia-dnd.rules.JournalEntry.2pzEa0ZH8CFn7sOC.JournalEntryPage.AV72Glo5U2ymdsCF]{Path of Wild Magic}</strong></p></li></ul><h3>@UUID[Compendium.materia-dnd.rules.JournalEntry.gnuh2kue9uqZpA72.JournalEntryPage.m2vfXnWW6gdwj81s]{Bard}</h3><p>An inspiring magician whose power echoes the music of creation.</p><p><em>Subclasses</em>:</p><ul><li><p><strong>@UUID[Compendium.materia-dnd.rules.JournalEntry.gnuh2kue9uqZpA72.JournalEntryPage.UhQPt1xc03N4X8I4]{College of Creation}</strong></p></li><li><p><strong>@UUID[Compendium.materia-dnd.rules.JournalEntry.gnuh2kue9uqZpA72.JournalEntryPage.S6UzXdas4IElUQzW]{College of Eloquence}</strong></p></li><li><p><strong>@UUID[Compendium.materia-dnd.rules.JournalEntry.gnuh2kue9uqZpA72.JournalEntryPage.gPOVGlFSQEZSmJd1]{College of Glamour}</strong></p></li><li><p><strong>@UUID[Compendium.materia-dnd.rules.JournalEntry.gnuh2kue9uqZpA72.JournalEntryPage.e6H9auH6FQcZvME0]{College of Lore}</strong></p></li><li><p><strong>@UUID[Compendium.materia-dnd.rules.JournalEntry.gnuh2kue9uqZpA72.JournalEntryPage.yWHX75Y9kDVS5OeC]{College of Spirits}</strong></p></li><li><p><strong>@UUID[Compendium.materia-dnd.rules.JournalEntry.gnuh2kue9uqZpA72.JournalEntryPage.KNH1jPQO9L88uPg1]{College of Swords}</strong></p></li><li><p><strong>@UUID[Compendium.materia-dnd.rules.JournalEntry.gnuh2kue9uqZpA72.JournalEntryPage.uiQoxQdJoyTNC3Yk]{College of Valor}</strong></p></li><li><p><strong>@UUID[Compendium.materia-dnd.rules.JournalEntry.gnuh2kue9uqZpA72.JournalEntryPage.01PxNIRdFXDUFe2I]{College of Whispers}</strong></p></li></ul><h3>@UUID[Compendium.materia-dnd.rules.JournalEntry.ElBz2p3ZJr9bvayT.JournalEntryPage.BL3LC5XGZRggXBJA]{Blood Hunter}</h3><p>Willing to suffer whatever it takes to achieve victory, these adept warriors have forged themselves into a potent force dedicated to protecting the innocent.</p><p><em>Subclasses</em>:</p><ul><li><p><strong>@UUID[Compendium.materia-dnd.rules.JournalEntry.ElBz2p3ZJr9bvayT.JournalEntryPage.AzOjBtTXeOZNF7av]{Order of the Ghostslayer}</strong></p></li><li><p><strong>@UUID[Compendium.materia-dnd.rules.JournalEntry.ElBz2p3ZJr9bvayT.JournalEntryPage.heufd4H3QZFq99be]{Order of the Lycan}</strong></p></li><li><p><strong>@UUID[Compendium.materia-dnd.rules.JournalEntry.ElBz2p3ZJr9bvayT.JournalEntryPage.oaFCEtWRJqMGAM6G]{Order of the Mutant}</strong></p></li><li><p><strong>@UUID[Compendium.materia-dnd.rules.JournalEntry.ElBz2p3ZJr9bvayT.JournalEntryPage.of4y7IYfUrlNhVgZ]{Order of the Profane Soul}</strong></p></li></ul><h3>@UUID[Compendium.materia-dnd.rules.JournalEntry.iP1dkRR5XjXBzGp6]{Cleric}</h3><p>A priestly champion who wields divine magic in service of a higher power.</p><p><em>Subclasses</em>:</p><ul><li><p><strong>@UUID[Compendium.materia-dnd.rules.JournalEntry.iP1dkRR5XjXBzGp6.JournalEntryPage.UPFkfgEDHqCm5wgA]{Arcana Domain}</strong></p></li><li><p><strong>@UUID[Compendium.materia-dnd.rules.JournalEntry.iP1dkRR5XjXBzGp6.JournalEntryPage.NzA9LgOPhcwBns9a]{Death Domain}</strong></p></li><li><p><strong>@UUID[Compendium.materia-dnd.rules.JournalEntry.iP1dkRR5XjXBzGp6.JournalEntryPage.96ppQp2lTY5XSlXU]{Forge Domain}</strong></p></li><li><p><strong>@UUID[Compendium.materia-dnd.rules.JournalEntry.iP1dkRR5XjXBzGp6.JournalEntryPage.NXrkFF8aJY8mAEog]{Grave Domain}</strong></p></li><li><p><strong>@UUID[Compendium.materia-dnd.rules.JournalEntry.iP1dkRR5XjXBzGp6.JournalEntryPage.8lkLFOrzW9Vz7drf]{Knowledge Domain}</strong></p></li><li><p><strong>@UUID[Compendium.materia-dnd.rules.JournalEntry.iP1dkRR5XjXBzGp6.JournalEntryPage.kEoc3kbBJozlbV7S]{Life Domain}</strong></p></li><li><p><strong>@UUID[Compendium.materia-dnd.rules.JournalEntry.iP1dkRR5XjXBzGp6.JournalEntryPage.6jJyEMT2lNl87dn1]{Light Domain}</strong></p></li><li><p><strong>@UUID[Compendium.materia-dnd.rules.JournalEntry.iP1dkRR5XjXBzGp6.JournalEntryPage.t8BWh1lPyj8fMrLN]{Nature Domain}</strong></p></li><li><p><strong>@UUID[Compendium.materia-dnd.rules.JournalEntry.iP1dkRR5XjXBzGp6.JournalEntryPage.CYaYCa8DPRwWTu5p]{Order Domain}</strong></p></li><li><p><strong>@UUID[Compendium.materia-dnd.rules.JournalEntry.iP1dkRR5XjXBzGp6.JournalEntryPage.nUQT3RYNIYrgoe9I]{Peace Domain}</strong></p></li><li><p><strong>@UUID[Compendium.materia-dnd.rules.JournalEntry.iP1dkRR5XjXBzGp6.JournalEntryPage.GOov9ATgJWZKXWvg]{Tempest Domain}</strong></p></li><li><p><strong>@UUID[Compendium.materia-dnd.rules.JournalEntry.iP1dkRR5XjXBzGp6.JournalEntryPage.HRSDS7vVKPj1nQ8O]{Trickery Domain}</strong></p></li><li><p><strong>@UUID[Compendium.materia-dnd.rules.JournalEntry.iP1dkRR5XjXBzGp6.JournalEntryPage.vaZCyjfrPvhmvxZn]{Twilight Domain}</strong></p></li><li><p><strong>@UUID[Compendium.materia-dnd.rules.JournalEntry.iP1dkRR5XjXBzGp6.JournalEntryPage.VgrUP5lLTUp9YZkq]{War Domain}</strong></p></li></ul><h3>@UUID[Compendium.materia-dnd.rules.JournalEntry.LZUwyLHk746KzSw4]{Druid}</h3><p>A priest of the Old Faith, wielding the powers of nature and adopting animal forms.</p><p><em>Subclasses</em>:</p><ul><li><p><strong>@UUID[Compendium.materia-dnd.rules.JournalEntry.LZUwyLHk746KzSw4.JournalEntryPage.M74tWCZhateEcKZ8]{Circle of Dreams}</strong></p></li><li><p><strong>@UUID[Compendium.materia-dnd.rules.JournalEntry.LZUwyLHk746KzSw4.JournalEntryPage.eDSscE0l1z3ByBiM]{Circle of Spores}</strong></p></li><li><p><strong>@UUID[Compendium.materia-dnd.rules.JournalEntry.LZUwyLHk746KzSw4.JournalEntryPage.O47U2sjtK3VitKwz]{Circle of Stars}</strong></p></li><li><p><strong>@UUID[Compendium.materia-dnd.rules.JournalEntry.LZUwyLHk746KzSw4.JournalEntryPage.x1AOINrVHyinYsOp]{Circle of the Land}</strong></p></li><li><p><strong>@UUID[Compendium.materia-dnd.rules.JournalEntry.LZUwyLHk746KzSw4.JournalEntryPage.TctmOHKYfxippxwB]{Circle of the Moon}</strong></p></li><li><p><strong>@UUID[Compendium.materia-dnd.rules.JournalEntry.LZUwyLHk746KzSw4.JournalEntryPage.rP7qocA9D3BpfmAL]{Circle of the Shepherd}</strong></p></li><li><p><strong>@UUID[Compendium.materia-dnd.rules.JournalEntry.LZUwyLHk746KzSw4.JournalEntryPage.XtH2O0f7fXlbdewU]{Circle of Wildfire}</strong></p></li></ul><h3>@UUID[Compendium.materia-dnd.rules.JournalEntry.6ZJMLuMjQhjacgaz]{Fighter}</h3><p>A master of martial combat, skilled with a variety of weapons and armor.</p><p><em>Subclasses</em>:</p><ul><li><p><strong>@UUID[Compendium.materia-dnd.rules.JournalEntry.6ZJMLuMjQhjacgaz.JournalEntryPage.dtCCFEhlgrZxof3d]{Arcane Archer}</strong></p></li><li><p><strong>@UUID[Compendium.materia-dnd.rules.JournalEntry.6ZJMLuMjQhjacgaz.JournalEntryPage.S7nV3Lsay8Wz6vgD]{Banneret}</strong></p></li><li><p><strong>@UUID[Compendium.materia-dnd.rules.JournalEntry.6ZJMLuMjQhjacgaz.JournalEntryPage.qcHNiHQzdpHFEI4o]{Cavalier}</strong></p></li><li><p><strong>@UUID[Compendium.materia-dnd.rules.JournalEntry.6ZJMLuMjQhjacgaz.JournalEntryPage.M2GXRFzhnOMmkzlC]{Champion}</strong></p></li><li><p><strong>@UUID[Compendium.materia-dnd.rules.JournalEntry.6ZJMLuMjQhjacgaz.JournalEntryPage.YtPFwVFyHEuJtz3T]{Echo Knight}</strong></p></li><li><p><strong>@UUID[Compendium.materia-dnd.rules.JournalEntry.6ZJMLuMjQhjacgaz.JournalEntryPage.FuyxpH6EwUFaV9qH]{Eldritch Knight}</strong></p></li><li><p><strong>@UUID[Compendium.materia-dnd.rules.JournalEntry.6ZJMLuMjQhjacgaz.JournalEntryPage.KLBgTVr6sXibdlS1]{Psi Warrior}</strong></p></li><li><p><strong>@UUID[Compendium.materia-dnd.rules.JournalEntry.6ZJMLuMjQhjacgaz.JournalEntryPage.rZkhAg95XTn3TyQZ]{Rune Knight}</strong></p></li><li><p><strong>@UUID[Compendium.materia-dnd.rules.JournalEntry.6ZJMLuMjQhjacgaz.JournalEntryPage.GZULd6hnbcsbFRGG]{Samurai}</strong></p></li></ul><h3>@UUID[Compendium.materia-dnd.rules.JournalEntry.U7eNQT2J7Onszv3y]{Monk}</h3><p>A master of martial arts, harnessing the power of the body in pursuit of physical and spiritual perfection.</p><p><em>Subclasses</em>:</p><ul><li><p><strong>@UUID[Compendium.materia-dnd.rules.JournalEntry.U7eNQT2J7Onszv3y.JournalEntryPage.PrZwiA2cb9CCfcOQ]{Way of Mercy}</strong></p></li><li><p><strong>@UUID[Compendium.materia-dnd.rules.JournalEntry.U7eNQT2J7Onszv3y.JournalEntryPage.WFzSvx14dUNz7J35]{Way of Shadow}</strong></p></li><li><p><strong>@UUID[Compendium.materia-dnd.rules.JournalEntry.U7eNQT2J7Onszv3y.JournalEntryPage.qNTOxROvTTIgF5cL]{Way of the Ascended Dragon}</strong></p></li><li><p><strong>@UUID[Compendium.materia-dnd.rules.JournalEntry.U7eNQT2J7Onszv3y.JournalEntryPage.bcS8IdTfDkHxF1lg]{Way of the Astral Self}</strong></p></li><li><p><strong>@UUID[Compendium.materia-dnd.rules.JournalEntry.U7eNQT2J7Onszv3y.JournalEntryPage.yy2okKf0EGWSQen7]{Way of the Cobalt Soul}</strong></p></li><li><p><strong>@UUID[Compendium.materia-dnd.rules.JournalEntry.U7eNQT2J7Onszv3y.JournalEntryPage.ywzCB2tuivJ2wc1j]{Way of the Drunken Master}</strong></p></li><li><p><strong>@UUID[Compendium.materia-dnd.rules.JournalEntry.U7eNQT2J7Onszv3y.JournalEntryPage.GXCCFVv7KIgadVhu]{Way of the Elements}</strong></p></li><li><p><strong>@UUID[Compendium.materia-dnd.rules.JournalEntry.U7eNQT2J7Onszv3y.JournalEntryPage.1f9rj342IoVkovYt]{Way of the Kensei}</strong></p></li><li><p><strong>@UUID[Compendium.materia-dnd.rules.JournalEntry.U7eNQT2J7Onszv3y.JournalEntryPage.LkfAie004tp3i7Tl]{Way of the Long Death}</strong></p></li><li><p><strong>@UUID[Compendium.materia-dnd.rules.JournalEntry.U7eNQT2J7Onszv3y.JournalEntryPage.N4dVRjvdwBLpYo1Q]{Way of the Open Hand}</strong></p></li><li><p><strong>@UUID[Compendium.materia-dnd.rules.JournalEntry.U7eNQT2J7Onszv3y.JournalEntryPage.utidgSgGdGAkvaxA]{Way of the Sun Soul}</strong></p></li></ul><h3>@UUID[Compendium.materia-dnd.rules.JournalEntry.iZNDQAnjPjioquhr]{Paladin}</h3><p>A holy warrior bound to a sacred oath.</p><p><em>Subclasses</em>:</p><ul><li><p><strong>@UUID[Compendium.materia-dnd.rules.JournalEntry.iZNDQAnjPjioquhr.JournalEntryPage.MmTdEr4bMotSmNBh]{Oath of Conquest}</strong></p></li><li><p><strong>@UUID[Compendium.materia-dnd.rules.JournalEntry.iZNDQAnjPjioquhr.JournalEntryPage.Q51IMEfHqOZR4Z9c]{Oath of Devotion}</strong></p></li><li><p><strong>@UUID[Compendium.materia-dnd.rules.JournalEntry.iZNDQAnjPjioquhr.JournalEntryPage.PlIDJilixNeb3brd]{Oath of Glory}</strong></p></li><li><p><strong>@UUID[Compendium.materia-dnd.rules.JournalEntry.iZNDQAnjPjioquhr.JournalEntryPage.1phOpzNAbWXdv6ZA]{Oath of Redemption}</strong></p></li><li><p><strong>@UUID[Compendium.materia-dnd.rules.JournalEntry.iZNDQAnjPjioquhr.JournalEntryPage.irFXFxCy98R1DJ12]{Oath of the Ancients}</strong></p></li><li><p><strong>@UUID[Compendium.materia-dnd.rules.JournalEntry.iZNDQAnjPjioquhr.JournalEntryPage.jiT4XfStwQFKOkSc]{Oath of the Crown}</strong></p></li><li><p><strong>@UUID[Compendium.materia-dnd.rules.JournalEntry.iZNDQAnjPjioquhr.JournalEntryPage.NSwstHjFSSgybgxw]{Oath of the Watchers}</strong></p></li><li><p><strong>@UUID[Compendium.materia-dnd.rules.JournalEntry.iZNDQAnjPjioquhr.JournalEntryPage.HB30u0iOgGsUX5pS]{Oath of Vengeance}</strong></p></li><li><p><strong>@UUID[Compendium.materia-dnd.rules.JournalEntry.iZNDQAnjPjioquhr.JournalEntryPage.9C0XJ3uEphd4ry5m]{Oathbreaker}</strong></p></li></ul><h3>@UUID[Compendium.materia-dnd.rules.JournalEntry.GUdhw3Fk1kAUQn8Q]{Ranger}</h3><p>A warrior who combats threats on the edges of civilization.</p><p><em>Subclasses</em>:</p><ul><li><p><strong>@UUID[Compendium.materia-dnd.rules.JournalEntry.GUdhw3Fk1kAUQn8Q.JournalEntryPage.6r9HFxWLYE3snvrY]{Beast Master}</strong></p></li><li><p><strong>@UUID[Compendium.materia-dnd.rules.JournalEntry.GUdhw3Fk1kAUQn8Q.JournalEntryPage.UJlJiRhaY9ACaHAy]{Drakewarden}</strong></p></li><li><p><strong>@UUID[Compendium.materia-dnd.rules.JournalEntry.GUdhw3Fk1kAUQn8Q.JournalEntryPage.DNJKLEo71TfUHHAI]{Fey Wanderer}</strong></p></li><li><p><strong>@UUID[Compendium.materia-dnd.rules.JournalEntry.GUdhw3Fk1kAUQn8Q.JournalEntryPage.MEp5Gy8lavxaAJhe]{Gloom Stalker}</strong></p></li><li><p><strong>@UUID[Compendium.materia-dnd.rules.JournalEntry.GUdhw3Fk1kAUQn8Q.JournalEntryPage.rCN0Xzvy7wfvhM3W]{Horizon Walker}</strong></p></li><li><p><strong>@UUID[Compendium.materia-dnd.rules.JournalEntry.GUdhw3Fk1kAUQn8Q.JournalEntryPage.WLRPrEzlj3T5owCu]{Hunter}</strong></p></li><li><p><strong>@UUID[Compendium.materia-dnd.rules.JournalEntry.GUdhw3Fk1kAUQn8Q.JournalEntryPage.LDXyAr9H1FqggwXS]{Monster Slayer}</strong></p></li><li><p><strong>@UUID[Compendium.materia-dnd.rules.JournalEntry.GUdhw3Fk1kAUQn8Q.JournalEntryPage.vMixN5laWpL5gwM0]{Swarmkeeper}</strong></p></li></ul><h3>@UUID[Compendium.materia-dnd.rules.JournalEntry.C9dlXNSVQ4UFzG0C]{Rogue}</h3><p>A scoundrel who uses stealth and trickery to overcome obstacles and enemies.</p><p><em>Subclasses</em>:</p><ul><li><p><strong>@UUID[Compendium.materia-dnd.rules.JournalEntry.C9dlXNSVQ4UFzG0C.JournalEntryPage.vSZ5dFxHx3HPmv4u]{Arcane Trickster}</strong></p></li><li><p><strong>@UUID[Compendium.materia-dnd.rules.JournalEntry.C9dlXNSVQ4UFzG0C.JournalEntryPage.9DNiXrX8jwONpCFe]{Assassin}</strong></p></li><li><p><strong>@UUID[Compendium.materia-dnd.rules.JournalEntry.C9dlXNSVQ4UFzG0C.JournalEntryPage.Jl4agb3KpZlGaEy8]{Inquisitive}</strong></p></li><li><p><strong>@UUID[Compendium.materia-dnd.rules.JournalEntry.C9dlXNSVQ4UFzG0C.JournalEntryPage.jmQM40ITjEXfSnUa]{Mastermind}</strong></p></li><li><p><strong>@UUID[Compendium.materia-dnd.rules.JournalEntry.C9dlXNSVQ4UFzG0C.JournalEntryPage.n0EWNEbGzqmlHfuP]{Phantom}</strong></p></li><li><p><strong>@UUID[Compendium.materia-dnd.rules.JournalEntry.C9dlXNSVQ4UFzG0C.JournalEntryPage.K63w1lMWbJGUXSDF]{Scout}</strong></p></li><li><p><strong>@UUID[Compendium.materia-dnd.rules.JournalEntry.C9dlXNSVQ4UFzG0C.JournalEntryPage.I6GHBML8q1Ww5mW2]{Soulknife}</strong></p></li><li><p><strong>@UUID[Compendium.materia-dnd.rules.JournalEntry.C9dlXNSVQ4UFzG0C.JournalEntryPage.J7QZn7GAI8WWuKOH]{Swashbuckler}</strong></p></li><li><p><strong>@UUID[Compendium.materia-dnd.rules.JournalEntry.C9dlXNSVQ4UFzG0C.JournalEntryPage.tpjcOtqORTWDPYw3]{Thief}</strong></p></li></ul><h3>@UUID[Compendium.materia-dnd.rules.JournalEntry.gMj3ebxhdppsYFsc.JournalEntryPage.czEwZ94kVSOX4JNp]{Sorcerer}</h3><p>A spellcaster who draws on inherent magic from a gift or bloodline.</p><p><em>Subclasses</em>:</p><ul><li><p><strong>@UUID[Compendium.materia-dnd.rules.JournalEntry.gMj3ebxhdppsYFsc.JournalEntryPage.CY6RI4egxjAMya2c]{Aberrant Mind}</strong></p></li><li><p><strong>@UUID[Compendium.materia-dnd.rules.JournalEntry.gMj3ebxhdppsYFsc.JournalEntryPage.nzyYN88Nde3XLGy2]{Clockwork Soul}</strong></p></li><li><p><strong>@UUID[Compendium.materia-dnd.rules.JournalEntry.gMj3ebxhdppsYFsc.JournalEntryPage.E0rO7p8BZe7C28Bu]{Divine Soul}</strong></p></li><li><p><strong>@UUID[Compendium.materia-dnd.rules.JournalEntry.gMj3ebxhdppsYFsc.JournalEntryPage.q7rq7H0HdNXt6B3A]{Draconic Bloodline}</strong></p></li><li><p><strong>@UUID[Compendium.materia-dnd.rules.JournalEntry.gMj3ebxhdppsYFsc.JournalEntryPage.LYmFCZ4Tb6Daa756]{Shadow Magic}</strong></p></li><li><p><strong>@UUID[Compendium.materia-dnd.rules.JournalEntry.gMj3ebxhdppsYFsc.JournalEntryPage.RWEnwgCTfzwugkIZ]{Storm Sorcery}</strong></p></li><li><p><strong>@UUID[Compendium.materia-dnd.rules.JournalEntry.gMj3ebxhdppsYFsc.JournalEntryPage.BoJvitdsFAidAwo9]{Wild Magic}</strong></p></li></ul><h3>@UUID[Compendium.materia-dnd.rules.JournalEntry.oX2Zl9pDIcTlA1O7.JournalEntryPage.LZq7dBzQ9Xm20qdg]{Warlock}</h3><p>A wielder of magic that is derived from a bargain with an extraplanar entity.</p><p><em>Subclasses</em>:</p><ul><li><p><strong>@UUID[Compendium.materia-dnd.rules.JournalEntry.oX2Zl9pDIcTlA1O7.JournalEntryPage.pIPRcYPh8EmWw3S7]{The Archfey}</strong></p></li><li><p><strong>@UUID[Compendium.materia-dnd.rules.JournalEntry.oX2Zl9pDIcTlA1O7.JournalEntryPage.Ljztj9gwNFOUsJJX]{The Celestial}</strong></p></li><li><p><strong>@UUID[Compendium.materia-dnd.rules.JournalEntry.oX2Zl9pDIcTlA1O7.JournalEntryPage.TNeu0KOfNvpFZVUD]{The Fathomless}</strong></p></li><li><p><strong>@UUID[Compendium.materia-dnd.rules.JournalEntry.oX2Zl9pDIcTlA1O7.JournalEntryPage.6o3G0PKA5L7xDnN5]{The Fiend}</strong></p></li><li><p><strong>@UUID[Compendium.materia-dnd.rules.JournalEntry.oX2Zl9pDIcTlA1O7.JournalEntryPage.PDqXwcBFtF31Mk1O]{The Genie}</strong></p></li><li><p><strong>@UUID[Compendium.materia-dnd.rules.JournalEntry.oX2Zl9pDIcTlA1O7.JournalEntryPage.vTx5pKDxuLeROwQF]{The Great Old One}</strong></p></li><li><p><strong>@UUID[Compendium.materia-dnd.rules.JournalEntry.oX2Zl9pDIcTlA1O7.JournalEntryPage.fsvViGEw0pu7Qf9i]{The Hexblade}</strong></p></li><li><p><strong>@UUID[Compendium.materia-dnd.rules.JournalEntry.oX2Zl9pDIcTlA1O7.JournalEntryPage.vLeKQ6Ou57SQVnbQ]{The Undead}</strong></p></li><li><p><strong>@UUID[Compendium.materia-dnd.rules.JournalEntry.oX2Zl9pDIcTlA1O7.JournalEntryPage.KcStKCoO87Tq4Lqx]{The Undying}</strong></p></li></ul><h3>@UUID[Compendium.materia-dnd.rules.JournalEntry.GXDljzQij4Cv1u1e.JournalEntryPage.ZrcM7hR5XMat2qKa]{Warlord}</h3><p>A charismatic leader with equal parts inspiration and martial prowess.</p><p><em>Subclasses</em>:</p><ul><li><p><strong>@UUID[Compendium.materia-dnd.rules.JournalEntry.GXDljzQij4Cv1u1e.JournalEntryPage.shGwxLilEyPbSxI3]{Battlefront Marshal}</strong></p></li><li><p><strong>@UUID[Compendium.materia-dnd.rules.JournalEntry.GXDljzQij4Cv1u1e.JournalEntryPage.XIOBX36nyRC8aWTK]{Icon of Victory}</strong></p></li><li><p><strong>@UUID[Compendium.materia-dnd.rules.JournalEntry.GXDljzQij4Cv1u1e.JournalEntryPage.2rZjb3iVuGS7Xvnn]{Magus Chief}</strong></p></li><li><p><strong>@UUID[Compendium.materia-dnd.rules.JournalEntry.GXDljzQij4Cv1u1e.JournalEntryPage.d41omLD4AyK7WTNO]{Tactician}</strong></p></li><li><p><strong>@UUID[Compendium.materia-dnd.rules.JournalEntry.GXDljzQij4Cv1u1e.JournalEntryPage.DWLH9p6uF5CdsPZ2]{Warbrave}</strong></p></li></ul><h3>@UUID[Compendium.materia-dnd.rules.JournalEntry.Ko6oQhoTaw2ATSvp.JournalEntryPage.1D5VCnuLYBek4cqz]{Wizard}</h3><p>A scholarly magic-user capable of manipulating the structures of reality.</p><p><em>Subclasses</em>:</p><ul><li><p><strong>@UUID[Compendium.materia-dnd.rules.JournalEntry.Ko6oQhoTaw2ATSvp.JournalEntryPage.PQw0EnsjBy57BbKb]{Bladesinging}</strong></p></li><li><p><strong>@UUID[Compendium.materia-dnd.rules.JournalEntry.Ko6oQhoTaw2ATSvp.JournalEntryPage.phkOnbCmX9pNCWUs]{Chronurgy Magic}</strong></p></li><li><p><strong>@UUID[Compendium.materia-dnd.rules.JournalEntry.Ko6oQhoTaw2ATSvp.JournalEntryPage.1T1ApQMvc4LZpHVK]{Graviturgy Magic}</strong></p></li><li><p><strong>@UUID[Compendium.materia-dnd.rules.JournalEntry.Ko6oQhoTaw2ATSvp.JournalEntryPage.oNmxyDUa8AWcy4tk]{Order of Scribes}</strong></p></li><li><p><strong>@UUID[Compendium.materia-dnd.rules.JournalEntry.Ko6oQhoTaw2ATSvp.JournalEntryPage.AkxA0QefUWgjqNpb]{School of Anjuration}</strong></p></li><li><p><strong>@UUID[Compendium.materia-dnd.rules.JournalEntry.Ko6oQhoTaw2ATSvp.JournalEntryPage.xe20tq072lBwiEvG]{School of Conjuration}</strong></p></li><li><p><strong>@UUID[Compendium.materia-dnd.rules.JournalEntry.Ko6oQhoTaw2ATSvp.JournalEntryPage.9BwD3AOHah9ZRJyF]{School of Divination}</strong></p></li><li><p><strong>@UUID[Compendium.materia-dnd.rules.JournalEntry.Ko6oQhoTaw2ATSvp.JournalEntryPage.fcu4JbiJWNxLx9Rv]{School of Enchantment}</strong></p></li><li><p><strong>@UUID[Compendium.materia-dnd.rules.JournalEntry.Ko6oQhoTaw2ATSvp.JournalEntryPage.hD2NrxjvhqFmfVXE]{School of Evocation}</strong></p></li><li><p><strong>@UUID[Compendium.materia-dnd.rules.JournalEntry.Ko6oQhoTaw2ATSvp.JournalEntryPage.G7iRSN69Tv4gZDtJ]{School of Illusion}</strong></p></li><li><p><strong>@UUID[Compendium.materia-dnd.rules.JournalEntry.Ko6oQhoTaw2ATSvp.JournalEntryPage.8awXngnwG3dsBNps]{School of Necromancy}</strong></p></li><li><p><strong>@UUID[Compendium.materia-dnd.rules.JournalEntry.Ko6oQhoTaw2ATSvp.JournalEntryPage.scfDldQRsvAsRdHm]{School of Transmutation}</strong></p></li><li><p><strong>@UUID[Compendium.materia-dnd.rules.JournalEntry.Ko6oQhoTaw2ATSvp.JournalEntryPage.ZByxyGDirRH3f4b5]{War Magic}</strong></p></li></ul>"
      },
      "video": {
        "controls": true,
        "volume": 0.5
      },
      "src": null,
      "ownership": {
        "default": -1
      },
      "flags": {},
      "_stats": {
        "duplicateSource": null,
        "coreVersion": "12.331",
        "systemId": "dnd5e",
        "systemVersion": "4.1.1",
        "createdTime": 1731478237489,
        "modifiedTime": 1731555846712,
        "lastModifiedBy": "dnd5mbuilder0000"
      },
      "_key": "!journal.pages!H76xJMaOJFmWpDIm.xumDsH85X7KxLhTH"
    }
  ],
  "folder": null,
  "sort": 200000,
  "ownership": {
    "default": 0
  },
  "flags": {
    "dnd5e": {
      "type": "chapter",
      "position": 3
    }
  },
  "_stats": {
    "duplicateSource": null,
    "coreVersion": "12.331",
    "systemId": "dnd5e",
    "systemVersion": "4.1.1",
    "createdTime": 1731478142468,
    "modifiedTime": 1731839360782,
    "lastModifiedBy": "dnd5mbuilder0000"
  },
  "_key": "!journal!H76xJMaOJFmWpDIm"
}
