{
  "folder": "Aj5v7YZXX3c3aqB1",
  "name": "Aasimar",
  "type": "race",
  "_id": "Nmirx1iajHEIuxOT",
  "img": "icons/magic/light/explosion-star-glow-silhouette.webp",
  "system": {
    "description": {
      "value": "",
      "chat": ""
    },
    "source": {
      "book": "Materia"
    },
    "advancement": [
      {
        "type": "AbilityScoreImprovement",
        "_id": "ALx7kvinpHW448mC",
        "configuration": {
          "points": 3,
          "fixed": {
            "str": 0,
            "dex": 0,
            "con": 0,
            "int": 0,
            "wis": 0,
            "cha": 0
          },
          "cap": 2
        },
        "value": {
          "type": "asi"
        },
        "level": 0,
        "title": "",
        "icon": null
      },
      {
        "type": "Size",
        "_id": "t9f0Z3VCKt5Z0g0R",
        "configuration": {
          "sizes": [
            "med"
          ]
        },
        "level": 0,
        "value": {}
      },
      {
        "type": "Trait",
        "configuration": {
          "grants": [
            "languages:standard:common"
          ],
          "mode": "default",
          "allowReplacements": false,
          "choices": [
            {
              "count": 1,
              "pool": [
                "languages:*"
              ]
            }
          ],
          "hint": ""
        },
        "_id": "wfrchBtgawzg6cqw",
        "level": 0,
        "value": {
          "chosen": []
        },
        "title": "",
        "icon": null
      },
      {
        "_id": "6X9EcbY1yerKMW3Z",
        "type": "ItemGrant",
        "configuration": {
          "items": [
            {
              "uuid": "Compendium.materia-dnd.species.Item.MkPy3X2oSrg3EXFp"
            },
            {
              "uuid": "Compendium.materia-dnd.species.Item.zMjGmIM8CtDWbO6u"
            }
          ],
          "optional": false,
          "spell": null
        },
        "value": {},
        "level": 0,
        "title": "Features",
        "icon": null
      },
      {
        "_id": "V5UCgzXaimn64A3w",
        "type": "ItemChoice",
        "configuration": {
          "choices": {
            "0": 1
          },
          "allowDrops": true,
          "type": "spell",
          "pool": [
            {
              "uuid": "Compendium.materia-dnd.species.Item.UrwLVSz01MdQbHWo"
            },
            {
              "uuid": "Compendium.materia-dnd.species.Item.6XklQR9xEQVTp7CH"
            },
            {
              "uuid": "Compendium.materia-dnd.species.Item.3aEoo8EVxqad7buh"
            }
          ],
          "spell": {
            "ability": "",
            "preparation": "",
            "uses": {
              "max": "",
              "per": ""
            }
          },
          "hint": "You know the light cantrip. Intelligence, Wisdom, or Charisma is your spellcasting ability for these spells when you cast them with this trait (choose when you select this species).",
          "restriction": {
            "level": ""
          }
        },
        "value": {},
        "title": "Light Bearer",
        "icon": "icons/magic/light/torch-fire-orange.webp"
      },
      {
        "_id": "XildbtUaIh7Mnpsn",
        "type": "ItemChoice",
        "configuration": {
          "choices": {
            "3": 1
          },
          "allowDrops": true,
          "type": "feat",
          "pool": [
            {
              "uuid": "Compendium.materia-dnd.species.Item.tPbOPjnCek8YjdVR"
            },
            {
              "uuid": "Compendium.materia-dnd.species.Item.zjSMMuLZmO0YcWxl"
            },
            {
              "uuid": "Compendium.materia-dnd.species.Item.EMfzr14obhXdeist"
            }
          ],
          "spell": null,
          "hint": "When you reach 3rd level, choose one of the revelation options below. Thereafter, you can use a bonus action to unleash the celestial energy within yourself, gaining the benefits of that revelation. Your transformation lasts for 1 minute or until you end it as a bonus action. You can use this trait a number of times equal to half your proficiency bonus (rounded up), regaining all expended uses when you finish a long rest",
          "restriction": {
            "type": "race",
            "subtype": ""
          }
        },
        "value": {},
        "title": "Celestial Revelation",
        "icon": "icons/magic/holy/angel-winged-humanoid-blue.webp"
      },
      {
        "_id": "",
        "type": "ItemChoice",
        "configuration": {
          "choices": {
            "6": 1
          },
          "allowDrops": false,
          "type": "feat",
          "pool": [
            {
              "uuid": "Compendium.materia-dnd.feats.Item.dr155ucXiflsJL3A"
            },
            {
              "uuid": "Compendium.materia-dnd.feats.Item.gB8FgszzrlJa0Ds2"
            },
            {
              "uuid": "Compendium.materia-dnd.feats.Item.EiJQ245YG4Mn6oMG"
            },
            {
              "uuid": "Compendium.materia-dnd.feats.Item.GIRCJyqzqjPylCbk"
            },
            {
              "uuid": "Compendium.materia-dnd.feats.Item.DByyzMEzN9RAuTKI"
            },
            {
              "uuid": "Compendium.materia-dnd.feats.Item.4JIQXAY0K0iF7VUN"
            },
            {
              "uuid": "Compendium.materia-dnd.feats.Item.e724e4wKHrEqmZVk"
            }
          ],
          "spell": null,
          "hint": "Core rule that provides a bonus based on character level and intelligence modifier at levels 6, 12, 18.  Does NOT apply retroactively and is not affected by temporary changes in Intelligence stat (from items or other buffs/debuffs)."
        },
        "value": {},
        "title": "INT Bonus",
        "icon": null
      },
      {
        "_id": "",
        "type": "ItemChoice",
        "configuration": {
          "choices": {
            "12": 1
          },
          "allowDrops": false,
          "type": "feat",
          "pool": [
            {
              "uuid": "Compendium.materia-dnd.feats.Item.mwm8RuMzWQL0MqK1"
            },
            {
              "uuid": "Compendium.materia-dnd.feats.Item.R25ikur9XI4YTp9A"
            },
            {
              "uuid": "Compendium.materia-dnd.feats.Item.kV7Op2e5amqmf3cq"
            },
            {
              "uuid": "Compendium.materia-dnd.feats.Item.mW9kfiO8t3zWrdXr"
            },
            {
              "uuid": "Compendium.materia-dnd.feats.Item.4uidh1shEaStPlqf"
            },
            {
              "uuid": "Compendium.materia-dnd.feats.Item.3owTwTFe2Vbtp6mV"
            },
            {
              "uuid": "Compendium.materia-dnd.feats.Item.PuLBlSImFP0YQjxt"
            }
          ],
          "spell": null,
          "hint": "Core rule that provides a bonus based on character level and intelligence modifier at levels 6, 12, 18.  Does NOT apply retroactively and is not affected by temporary changes in Intelligence stat (from items or other buffs/debuffs)."
        },
        "value": {},
        "title": "INT Bonus",
        "icon": null
      },
      {
        "_id": "",
        "type": "ItemChoice",
        "configuration": {
          "choices": {
            "18": 1
          },
          "allowDrops": false,
          "type": "feat",
          "pool": [
            {
              "uuid": "Compendium.materia-dnd.feats.Item.iX52QGxfrsoKoZVE"
            },
            {
              "uuid": "Compendium.materia-dnd.feats.Item.INdCbKNtjhyra9px"
            },
            {
              "uuid": "Compendium.materia-dnd.feats.Item.ItCqTyiALrJzJjro"
            },
            {
              "uuid": "Compendium.materia-dnd.feats.Item.j6f3RjlgmJC6kCyo"
            },
            {
              "uuid": "Compendium.materia-dnd.feats.Item.4uidh1shEaStPlqf"
            },
            {
              "uuid": "Compendium.materia-dnd.feats.Item.7GpkJb0TFIMOG97c"
            },
            {
              "uuid": "Compendium.materia-dnd.feats.Item.pjDsrDYXoL1d93tW"
            }
          ],
          "spell": null,
          "hint": "Core rule that provides a bonus based on character level and intelligence modifier at levels 6, 12, 18.  Does NOT apply retroactively and is not affected by temporary changes in Intelligence stat (from items or other buffs/debuffs)."
        },
        "value": {},
        "title": "INT Bonus",
        "icon": null
      }
    ],
    "movement": {
      "burrow": null,
      "climb": null,
      "fly": null,
      "swim": null,
      "walk": 30,
      "units": null,
      "hover": false
    },
    "senses": {
      "darkvision": 60,
      "blindsight": null,
      "tremorsense": null,
      "truesight": null,
      "units": null,
      "special": ""
    },
    "type": {
      "value": "humanoid"
    }
  },
  "effects": [],
  "sort": 0,
  "ownership": {
    "default": 0
  },
  "flags": {},
  "_stats": {
    "systemId": "dnd5e",
    "systemVersion": "3.1.1",
    "coreVersion": "12.325",
    "createdTime": 1708368890728,
    "modifiedTime": 1712147040295,
    "lastModifiedBy": "dnd5mbuilder0000",
    "compendiumSource": null,
    "duplicateSource": null
  },
  "_key": "!items!Nmirx1iajHEIuxOT"
}
